sio_messenger/__init__.py
sio_messenger/exception.py
sio_messenger/instance.py
sio_messenger/type.py
sio_messenger/version.py
sio_messenger-2024.5.dist-info/METADATA
sio_messenger-2024.5.dist-info/WHEEL
sio_messenger-2024.5.dist-info/top_level.txt
sio_messenger-2024.5.dist-info/RECORD
