Metadata-Version: 2.1
Name: sio-messenger
Version: 2024.5
Summary: Simple Inter-Object Messenger similar to the Signal-and-Slot Mechanism
Home-page: https://src.koda.cnrs.fr/eric.debreuve/sio-messenger/
Author: Eric Debreuve
Author-email: eric.debreuve@cnrs.fr
License: CeCILL-2.1
Project-URL: Documentation, https://src.koda.cnrs.fr/eric.debreuve/sio-messenger/-/wikis/home
Project-URL: Source, https://src.koda.cnrs.fr/eric.debreuve/sio-messenger/
Keywords: signal,slot,inter-object communication
Classifier: Topic :: Software Development
Classifier: Intended Audience :: Developers
Classifier: License :: OSI Approved :: CEA CNRS Inria Logiciel Libre License, version 2.1 (CeCILL-2.1)
Classifier: Programming Language :: Python :: 3
Classifier: Development Status :: 5 - Production/Stable
Requires-Python: >=3.11
